{"id": "rentomatic.use_cases.request_objects", "path": "rentomatic\\use_cases\\request_objects.py", "mtime": 1589017032, "size": 781, "hash": "43f20df3d43f77f8357744f5bc55384bf11a2907bff048d5bc40079d298d9a9b", "data_mtime": 1589017035, "dependencies": ["collections", "rentomatic.shared", "rentomatic.shared.request_object", "typing", "builtins", "abc"], "suppressed": [], "options": {"disallow_incomplete_defs": false, "implicit_reexport": true, "ignore_errors": false, "warn_unused_ignores": false, "bazel": false, "always_false": [], "strict_optional": true, "strict_optional_whitelist": null, "follow_imports": "normal", "ignore_missing_imports": false, "warn_return_any": false, "disallow_subclassing_any": false, "disallow_untyped_decorators": false, "disallow_untyped_defs": false, "check_untyped_defs": false, "disallow_any_decorated": false, "warn_no_return": true, "follow_imports_for_stubs": false, "local_partial_types": false, "allow_redefinition": false, "disallow_any_expr": false, "platform": "win32", "disallow_any_generics": false, "strict_equality": false, "warn_unreachable": false, "plugins": [], "disallow_any_unimported": false, "disallow_any_explicit": false, "no_implicit_optional": false, "always_true": [], "allow_untyped_globals": false, "mypyc": false, "show_none_errors": true, "disallow_untyped_calls": false}, "dep_prios": [10, 20, 10, 5, 5, 30], "dep_lines": [1, 3, 3, 4, 1, 1], "interface_hash": "9e00bb06503fb1211bc4ccb2bc7cecf1258783c3760420d875a643c14b00fbff", "version_id": "0.770", "ignore_all": false, "plugin_data": null}